{"variables": {"N0_7muVerMo": ["StrongUp", "WeakUp", "Neutral", "Down"], "SubjVertMo": ["StronUp", "WeakUp", "Neutral", "Down"], "QGVertMotion": ["StrongUp", "WeakUp", "Neutral", "Down"], "CombVerMo": ["StrongUp", "WeakUp", "Neutral", "Down"], "AreaMeso_ALS": ["StrongUp", "WeakUp", "Neutral", "Down"], "SatContMoist": ["VeryWet", "Wet", "Neutral", "Dry"], "RaoContMoist": ["VeryWet", "Wet", "Neutral", "Dry"], "CombMoisture": ["VeryWet", "Wet", "Neutral", "Dry"], "AreaMoDryAir": ["VeryWet", "Wet", "Neutral", "Dry"], "VISCloudCov": ["Cloudy", "PC", "Clear"], "IRCloudCover": ["Cloudy", "PC", "Clear"], "CombClouds": ["Cloudy", "PC", "Clear"], "CldShadeOth": ["Cloudy", "PC", "Clear"], "AMInstabMt": ["None", "Weak", "Strong"], "InsInMt": ["None", "Weak", "Strong"], "WndHodograph": ["DCVZFavor", "StrongWest", "Westerly", "Other"], "OutflowFrMt": ["None", "Weak", "Strong"], "MorningBound": ["None", "Weak", "Strong"], "Boundaries": ["None", "Weak", "Strong"], "CldShadeConv": ["None", "Some", "Marked"], "CompPlFcst": ["IncCapDecIns", "LittleChange", "DecCapIncIns"], "CapChange": ["Decreasing", "LittleChange", "Increasing"], "LoLevMoistAd": ["StrongPos", "WeakPos", "Neutral", "Negative"], "InsChange": ["Decreasing", "LittleChange", "Increasing"], "MountainFcst": ["NIL", "SIG", "SVR"], "Date": ["May15_Jun14", "Jun15_Jul1", "Jul2_Jul15", "Jul16_Aug10", "Aug11_Aug20", "Aug20_Sep15"], "Scenario": ["A", "B", "C", "D", "E", "F", "G", "H", "I", "J", "K"], "ScenRelAMCIN": ["AB", "CThruK"], "MorningCIN": ["None", "PartInhibit", "Stifling", "TotalInhibit"], "AMCINInScen": ["LessThanAve", "Average", "MoreThanAve"], "CapInScen": ["LessThanAve", "Average", "MoreThanAve"], "ScenRelAMIns": ["ABI", "CDEJ", "F", "G", "H", "K"], "LIfr12ZDENSd": ["LIGt0", "N1GtLIGt_4", "N5GtLIGt_8", "LILt_8"], "AMDewptCalPl": ["Instability", "Neutral", "Stability"], "AMInsWliScen": ["LessUnstable", "Average", "MoreUnstable"], "InsSclInScen": ["LessUnstable", "Average", "MoreUnstable"], "ScenRel3_4": ["ACEFK", "B", "D", "GJ", "HI"], "LatestCIN": ["None", "PartInhibit", "Stifling", "TotalInhibit"], "LLIW": ["Unfavorable", "Weak", "Moderate", "Strong"], "CurPropConv": ["None", "Slight", "Moderate", "Strong"], "ScnRelPlFcst": ["A", "B", "C", "D", "E", "F", "G", "H", "I", "J", "K"], "PlainsFcst": ["NIL", "SIG", "SVR"], "N34StarFcst": ["NIL", "SIG", "SVR"], "R5Fcst": ["NIL", "SIG", "SVR"], "Dewpoints": ["LowEvrywhere", "LowAtStation", "LowSHighN", "LowNHighS", "LowMtsHighPl", "HighEvrywher", "Other"], "LowLLapse": ["CloseToDryAd", "Steep", "ModerateOrLe", "Stable"], "MeanRH": ["VeryMoist", "Average", "Dry"], "MidLLapse": ["CloseToDryAd", "Steep", "ModerateOrLe"], "MvmtFeatures": ["StrongFront", "MarkedUpper", "OtherRapid", "NoMajor"], "RHRatio": ["MoistMDryL", "DryMMoistL", "Other"], "SfcWndShfDis": ["DenvCyclone", "E_W_N", "E_W_S", "MovingFtorOt", "DryLine", "None", "Other"], "SynForcng": ["SigNegative", "NegToPos", "SigPositive", "PosToNeg", "LittleChange"], "TempDis": ["QStationary", "Moving", "None", "Other"], "WindAloft": ["LV", "SWQuad", "NWQuad", "AllElse"], "WindFieldMt": ["Westerly", "LVorOther"], "WindFieldPln": ["LV", "DenvCyclone", "LongAnticyc", "E_NE", "SEQuad", "WidespdDnsl"]}, "dependencies": {"CombVerMo": ["N0_7muVerMo", "SubjVertMo", "QGVertMotion"], "AreaMeso_ALS": ["CombVerMo"], "CombMoisture": ["SatContMoist", "RaoContMoist"], "AreaMoDryAir": ["AreaMeso_ALS", "CombMoisture"], "CombClouds": ["VISCloudCov", "IRCloudCover"], "CldShadeOth": ["AreaMoDryAir", "AreaMeso_ALS", "CombClouds"], "InsInMt": ["CldShadeOth", "AMInstabMt"], "OutflowFrMt": ["InsInMt", "WndHodograph"], "Boundaries": ["OutflowFrMt", "WndHodograph", "MorningBound"], "CldShadeConv": ["InsInMt", "WndHodograph"], "CompPlFcst": ["Boundaries", "CldShadeConv", "AreaMeso_ALS", "CldShadeOth"], "CapChange": ["CompPlFcst"], "InsChange": ["LoLevMoistAd", "CompPlFcst"], "MountainFcst": ["InsInMt"], "Scenario": ["Date"], "ScenRelAMCIN": ["Scenario"], "AMCINInScen": ["ScenRelAMCIN", "MorningCIN"], "CapInScen": ["AMCINInScen", "CapChange"], "ScenRelAMIns": ["Scenario"], "AMInsWliScen": ["ScenRelAMIns", "LIfr12ZDENSd", "AMDewptCalPl"], "InsSclInScen": ["AMInsWliScen", "InsChange"], "ScenRel3_4": ["Scenario"], "CurPropConv": ["LatestCIN", "LLIW"], "ScnRelPlFcst": ["Scenario"], "PlainsFcst": ["CurPropConv", "InsSclInScen", "CapInScen", "ScnRelPlFcst"], "N34StarFcst": ["ScenRel3_4", "PlainsFcst"], "R5Fcst": ["MountainFcst", "N34StarFcst"], "Dewpoints": ["Scenario"], "LowLLapse": ["Scenario"], "MeanRH": ["Scenario"], "MidLLapse": ["Scenario"], "MvmtFeatures": ["Scenario"], "RHRatio": ["Scenario"], "SfcWndShfDis": ["Scenario"], "SynForcng": ["Scenario"], "TempDis": ["Scenario"], "WindAloft": ["Scenario"], "WindFieldMt": ["Scenario"], "WindFieldPln": ["Scenario"]}}